localmd/__init__.py
localmd/dataset.py
localmd/decomposition.py
localmd/evaluation.py
localmd/pmd_loader.py
localmd/preprocessing_utils.py
localmd/visualization.py
localmd-0.0.4.dist-info/.ipynb_checkpoints/PKG-INFO-checkpoint
localmd-0.0.4.dist-info/.ipynb_checkpoints/SOURCES-checkpoint.txt
localmd-0.0.4.dist-info/.ipynb_checkpoints/dependency_links-checkpoint.txt
localmd-0.0.4.dist-info/LICENSE
localmd-0.0.4.dist-info/METADATA
localmd-0.0.4.dist-info/WHEEL
localmd-0.0.4.dist-info/top_level.txt
localmd-0.0.4.dist-info/RECORD
